README.md
setup.py
peruscp/__init__.py
peruscp.egg-info/PKG-INFO
peruscp.egg-info/SOURCES.txt
peruscp.egg-info/dependency_links.txt
peruscp.egg-info/requires.txt
peruscp.egg-info/top_level.txt
peruscp/eldni/__init__.py
peruscp/eldni/elDNI.py